[
  {
    "coin": "ETHUSDT",
    "price": 4405.83,
    "tp": 4387.7402,
    "sl": 4423.9198,
    "leverage": "6x",
    "pop": 60,
    "signal": "Sell",
    "ema_boost_applied": false,
    "estimated_profit": "2.05%",
    "analysis_log": {
      "buy_score": -10,
      "sell_score": 15,
      "initial_signal": "Sell",
      "base_score_ok": false,
      "confluence_ok": false,
      "vol_profile_ok": false,
      "market_trend_ok": true,
      "macd_conflict_ok": false,
      "profit_ceiling_ok": true,
      "min_profit_ok": true,
      "downgrade_reason": "N/A"
    },
    "indicators": {
      "rsi5m": 43.371472751236674,
      "macd5m": {
        "macd": -5.194593224653545,
        "signal": -7.720530406309484,
        "histogram": 2.525937181655939
      },
      "boll5m": {
        "upper": 4425.534085398821,
        "middle": 4403.2925,
        "lower": 4381.050914601178
      },
      "cci5m": 31.828912290271067,
      "marketTrend": -5,
      "volProfile": {
        "bullish_score": 3,
        "bearish_score": 0
      },
      "ema50_5m": 4421.637556314175
    }
  },
  {
    "coin": "BTCUSDT",
    "price": 117470.3,
    "tp": 117470.3,
    "sl": 117470.3,
    "leverage": "6x",
    "pop": 50,
    "signal": "Neutral",
    "ema_boost_applied": false,
    "estimated_profit": "0.00%",
    "analysis_log": {
      "buy_score": 15,
      "sell_score": 15,
      "profit_ceiling_ok": true,
      "min_profit_ok": false,
      "downgrade_reason": "N/A"
    },
    "indicators": {
      "rsi5m": 56.61287505982721,
      "macd5m": {
        "macd": -2.400584236573195,
        "signal": -30.119293147144596,
        "histogram": 27.7187089105714
      },
      "boll5m": {
        "upper": 117522.01945937633,
        "middle": 117344.38500000001,
        "lower": 117166.75054062369
      },
      "cci5m": 127.3642830788578,
      "marketTrend": -5,
      "volProfile": {
        "bullish_score": 0,
        "bearish_score": 3
      },
      "ema50_5m": 117441.42398062669
    }
  },
  {
    "coin": "SOLUSDT",
    "price": 186.81,
    "tp": 185.9508,
    "sl": 187.6692,
    "leverage": "6x",
    "pop": 60,
    "signal": "Sell",
    "ema_boost_applied": false,
    "estimated_profit": "2.30%",
    "analysis_log": {
      "buy_score": -10,
      "sell_score": 15,
      "initial_signal": "Sell",
      "base_score_ok": false,
      "confluence_ok": false,
      "vol_profile_ok": true,
      "market_trend_ok": true,
      "macd_conflict_ok": false,
      "profit_ceiling_ok": true,
      "min_profit_ok": true,
      "downgrade_reason": "N/A"
    },
    "indicators": {
      "rsi5m": 48.582704060098166,
      "macd5m": {
        "macd": -0.14529542295710485,
        "signal": -0.27101325074198307,
        "histogram": 0.12571782778487822
      },
      "boll5m": {
        "upper": 187.24812235224223,
        "middle": 186.45999999999998,
        "lower": 185.67187764775773
      },
      "cci5m": 91.7434547315957,
      "marketTrend": -5,
      "volProfile": {
        "bullish_score": 5,
        "bearish_score": 5
      },
      "ema50_5m": 187.14197151989583
    }
  },
  {
    "coin": "XRPUSDT",
    "price": 3.1206,
    "tp": 3.1068,
    "sl": 3.1344,
    "leverage": "9x",
    "pop": 89,
    "signal": "Sell",
    "ema_boost_applied": false,
    "estimated_profit": "2.21%",
    "analysis_log": {
      "buy_score": 5,
      "sell_score": 40,
      "initial_signal": "Sell",
      "base_score_ok": true,
      "confluence_ok": false,
      "vol_profile_ok": true,
      "market_trend_ok": true,
      "macd_conflict_ok": true,
      "profit_ceiling_ok": true,
      "min_profit_ok": true,
      "downgrade_reason": "N/A"
    },
    "indicators": {
      "rsi5m": 39.43336382311204,
      "macd5m": {
        "macd": -0.002799227449191477,
        "signal": -0.001358890924949229,
        "histogram": -0.001440336524242248
      },
      "boll5m": {
        "upper": 3.1424230791818237,
        "middle": 3.13009,
        "lower": 3.1177569208181763
      },
      "cci5m": -138.4346395145496,
      "marketTrend": -5,
      "volProfile": {
        "bullish_score": 0,
        "bearish_score": 3
      },
      "ema50_5m": 3.1273794119370764
    }
  },
  {
    "coin": "DOGEUSDT",
    "price": 0.2297,
    "tp": 0.2282,
    "sl": 0.2312,
    "leverage": "7x",
    "pop": 75,
    "signal": "Sell",
    "ema_boost_applied": false,
    "estimated_profit": "3.28%",
    "analysis_log": {
      "buy_score": 5,
      "sell_score": 15,
      "initial_signal": "Sell",
      "base_score_ok": false,
      "confluence_ok": false,
      "vol_profile_ok": true,
      "market_trend_ok": true,
      "macd_conflict_ok": true,
      "profit_ceiling_ok": true,
      "min_profit_ok": true,
      "downgrade_reason": "N/A"
    },
    "indicators": {
      "rsi5m": 36.50054741427938,
      "macd5m": {
        "macd": -0.0006999242238391323,
        "signal": -0.0006777166284649223,
        "histogram": -2.220759537421e-05
      },
      "boll5m": {
        "upper": 0.23248477721166927,
        "middle": 0.2306915,
        "lower": 0.22889822278833072
      },
      "cci5m": -86.47405623977495,
      "marketTrend": -5,
      "volProfile": {
        "bullish_score": 0,
        "bearish_score": 3
      },
      "ema50_5m": 0.23159603575402196
    }
  },
  {
    "coin": "ADAUSDT",
    "price": 0.9096,
    "tp": 0.9178,
    "sl": 0.9014,
    "leverage": "6x",
    "pop": 57,
    "signal": "Buy",
    "ema_boost_applied": false,
    "estimated_profit": "4.49%",
    "analysis_log": {
      "buy_score": 20,
      "sell_score": 15,
      "initial_signal": "Buy",
      "base_score_ok": true,
      "confluence_ok": true,
      "vol_profile_ok": false,
      "market_trend_ok": false,
      "profit_ceiling_ok": true,
      "min_profit_ok": true,
      "downgrade_reason": "N/A"
    },
    "indicators": {
      "rsi5m": 29.29519824532403,
      "macd5m": {
        "macd": -0.008867479538178458,
        "signal": -0.010390941633274474,
        "histogram": 0.0015234620950960159
      },
      "boll5m": {
        "upper": 0.9275658312270112,
        "middle": 0.912825,
        "lower": 0.8980841687729888
      },
      "cci5m": -33.78569409103892,
      "marketTrend": -5,
      "volProfile": {
        "bullish_score": 0,
        "bearish_score": 3
      },
      "ema50_5m": 0.9318037786147619
    }
  },
  {
    "coin": "ENAUSDT",
    "price": 0.7178,
    "tp": 0.7124,
    "sl": 0.7232,
    "leverage": "6x",
    "pop": 60,
    "signal": "Sell",
    "ema_boost_applied": false,
    "estimated_profit": "3.78%",
    "analysis_log": {
      "buy_score": -10,
      "sell_score": 15,
      "initial_signal": "Sell",
      "base_score_ok": false,
      "confluence_ok": false,
      "vol_profile_ok": true,
      "market_trend_ok": true,
      "macd_conflict_ok": false,
      "profit_ceiling_ok": true,
      "min_profit_ok": true,
      "downgrade_reason": "N/A"
    },
    "indicators": {
      "rsi5m": 42.918753373745425,
      "macd5m": {
        "macd": -0.0007930327617491351,
        "signal": -0.001011578498860883,
        "histogram": 0.00021854573711174784
      },
      "boll5m": {
        "upper": 0.723088045314791,
        "middle": 0.7195199999999999,
        "lower": 0.7159519546852089
      },
      "cci5m": -65.5526992287865,
      "marketTrend": -5,
      "volProfile": {
        "bullish_score": 0,
        "bearish_score": 3
      },
      "ema50_5m": 0.7221901265876001
    }
  },
  {
    "coin": "XNYUSDT",
    "price": 0.0252,
    "tp": 0.0245,
    "sl": 0.0259,
    "leverage": "6x",
    "pop": 60,
    "signal": "Sell",
    "ema_boost_applied": false,
    "estimated_profit": "13.96%",
    "analysis_log": {
      "buy_score": -10,
      "sell_score": 15,
      "initial_signal": "Sell",
      "base_score_ok": false,
      "confluence_ok": false,
      "vol_profile_ok": true,
      "market_trend_ok": true,
      "macd_conflict_ok": false,
      "profit_ceiling_ok": false,
      "min_profit_ok": true,
      "downgrade_reason": "N/A"
    },
    "indicators": {
      "rsi5m": 47.86162972870186,
      "macd5m": {
        "macd": -0.00024687891865601483,
        "signal": -0.00032644573261246534,
        "histogram": 7.956681395645052e-05
      },
      "boll5m": {
        "upper": 0.02559739876248571,
        "middle": 0.0250326,
        "lower": 0.024467801237514287
      },
      "cci5m": 54.85751827215315,
      "marketTrend": -5,
      "volProfile": {
        "bullish_score": 0,
        "bearish_score": 3
      },
      "ema50_5m": 0.02562283796008323
    }
  },
  {
    "coin": "SUIUSDT",
    "price": 3.7025,
    "tp": 3.6833,
    "sl": 3.7217,
    "leverage": "6x",
    "pop": 60,
    "signal": "Sell",
    "ema_boost_applied": false,
    "estimated_profit": "2.60%",
    "analysis_log": {
      "buy_score": -10,
      "sell_score": 15,
      "initial_signal": "Sell",
      "base_score_ok": false,
      "confluence_ok": false,
      "vol_profile_ok": true,
      "market_trend_ok": true,
      "macd_conflict_ok": false,
      "profit_ceiling_ok": true,
      "min_profit_ok": true,
      "downgrade_reason": "N/A"
    },
    "indicators": {
      "rsi5m": 46.556769119588914,
      "macd5m": {
        "macd": -0.0025784088872837785,
        "signal": -0.004233583998084737,
        "histogram": 0.0016551751108009587
      },
      "boll5m": {
        "upper": 3.719381918854849,
        "middle": 3.7013,
        "lower": 3.6832180811451507
      },
      "cci5m": 20.553887220555183,
      "marketTrend": -5,
      "volProfile": {
        "bullish_score": 5,
        "bearish_score": 5
      },
      "ema50_5m": 3.7107109251709436
    }
  },
  {
    "coin": "1000PEPEUSDT",
    "price": 0.0109,
    "tp": 0.0108,
    "sl": 0.0109,
    "leverage": "6x",
    "pop": 60,
    "signal": "Sell",
    "ema_boost_applied": false,
    "estimated_profit": "2.72%",
    "analysis_log": {
      "buy_score": -10,
      "sell_score": 15,
      "initial_signal": "Sell",
      "base_score_ok": false,
      "confluence_ok": false,
      "vol_profile_ok": false,
      "market_trend_ok": true,
      "macd_conflict_ok": false,
      "profit_ceiling_ok": true,
      "min_profit_ok": true,
      "downgrade_reason": "N/A"
    },
    "indicators": {
      "rsi5m": 54.90250734018012,
      "macd5m": {
        "macd": 7.2260604068504625e-06,
        "signal": 1.667490829720259e-06,
        "histogram": 5.558569577130203e-06
      },
      "boll5m": {
        "upper": 0.01092008312981053,
        "middle": 0.01085853,
        "lower": 0.01079697687018947
      },
      "cci5m": 84.3469522126395,
      "marketTrend": -5,
      "volProfile": {
        "bullish_score": 3,
        "bearish_score": 0
      },
      "ema50_5m": 0.010858709697080866
    }
  },
  {
    "coin": "MYXUSDT",
    "price": 1.9693,
    "tp": 1.9402,
    "sl": 1.9984,
    "leverage": "6x",
    "pop": 60,
    "signal": "Sell",
    "ema_boost_applied": false,
    "estimated_profit": "7.39%",
    "analysis_log": {
      "buy_score": -10,
      "sell_score": 15,
      "initial_signal": "Sell",
      "base_score_ok": false,
      "confluence_ok": false,
      "vol_profile_ok": true,
      "market_trend_ok": true,
      "macd_conflict_ok": true,
      "profit_ceiling_ok": false,
      "min_profit_ok": true,
      "downgrade_reason": "N/A"
    },
    "indicators": {
      "rsi5m": 52.7489188009873,
      "macd5m": {
        "macd": 0.004658421851786887,
        "signal": 0.007189474943885199,
        "histogram": -0.0025310530920983117
      },
      "boll5m": {
        "upper": 1.9818751652988291,
        "middle": 1.971925,
        "lower": 1.9619748347011707
      },
      "cci5m": -39.59390862944278,
      "marketTrend": -5,
      "volProfile": {
        "bullish_score": 0,
        "bearish_score": 3
      },
      "ema50_5m": 1.9507215671995346
    }
  },
  {
    "coin": "ALPINEUSDT",
    "price": 2.1298,
    "tp": 2.0733,
    "sl": 2.1863,
    "leverage": "6x",
    "pop": 60,
    "signal": "Sell",
    "ema_boost_applied": false,
    "estimated_profit": "13.26%",
    "analysis_log": {
      "buy_score": -10,
      "sell_score": 15,
      "initial_signal": "Sell",
      "base_score_ok": false,
      "confluence_ok": false,
      "vol_profile_ok": false,
      "market_trend_ok": true,
      "macd_conflict_ok": true,
      "profit_ceiling_ok": false,
      "min_profit_ok": true,
      "downgrade_reason": "N/A"
    },
    "indicators": {
      "rsi5m": 53.91588102701651,
      "macd5m": {
        "macd": 0.009632033822776886,
        "signal": 0.010550741247960958,
        "histogram": -0.0009187074251840715
      },
      "boll5m": {
        "upper": 2.154635989054176,
        "middle": 2.11991,
        "lower": 2.0851840109458237
      },
      "cci5m": 35.65568917981462,
      "marketTrend": -5,
      "volProfile": {
        "bullish_score": 3,
        "bearish_score": 0
      },
      "ema50_5m": 2.1000437681422475
    }
  },
  {
    "coin": "BNBUSDT",
    "price": 831.51,
    "tp": 829.1406,
    "sl": 833.8794,
    "leverage": "6x",
    "pop": 60,
    "signal": "Sell",
    "ema_boost_applied": false,
    "estimated_profit": "1.42%",
    "analysis_log": {
      "buy_score": -10,
      "sell_score": 15,
      "initial_signal": "Sell",
      "base_score_ok": false,
      "confluence_ok": false,
      "vol_profile_ok": true,
      "market_trend_ok": true,
      "macd_conflict_ok": false,
      "profit_ceiling_ok": true,
      "min_profit_ok": false,
      "downgrade_reason": "N/A"
    },
    "indicators": {
      "rsi5m": 51.53982163479424,
      "macd5m": {
        "macd": -0.5329785555817352,
        "signal": -1.0967602538879948,
        "histogram": 0.5637816983062596
      },
      "boll5m": {
        "upper": 833.2388675345568,
        "middle": 829.845,
        "lower": 826.4511324654433
      },
      "cci5m": 81.77530348720661,
      "marketTrend": -5,
      "volProfile": {
        "bullish_score": 0,
        "bearish_score": 3
      },
      "ema50_5m": 832.2362517190993
    }
  },
  {
    "coin": "LINKUSDT",
    "price": 21.61,
    "tp": 21.4884,
    "sl": 21.7316,
    "leverage": "6x",
    "pop": 60,
    "signal": "Sell",
    "ema_boost_applied": false,
    "estimated_profit": "2.81%",
    "analysis_log": {
      "buy_score": -10,
      "sell_score": 15,
      "initial_signal": "Sell",
      "base_score_ok": false,
      "confluence_ok": false,
      "vol_profile_ok": true,
      "market_trend_ok": true,
      "macd_conflict_ok": false,
      "profit_ceiling_ok": true,
      "min_profit_ok": true,
      "downgrade_reason": "N/A"
    },
    "indicators": {
      "rsi5m": 47.91524248177589,
      "macd5m": {
        "macd": -0.029241183513896374,
        "signal": -0.05282806128524495,
        "histogram": 0.023586877771348574
      },
      "boll5m": {
        "upper": 21.692522386701224,
        "middle": 21.56225,
        "lower": 21.431977613298773
      },
      "cci5m": 80.48668503214137,
      "marketTrend": -5,
      "volProfile": {
        "bullish_score": 0,
        "bearish_score": 3
      },
      "ema50_5m": 21.678317264429324
    }
  },
  {
    "coin": "FARTCOINUSDT",
    "price": 0.9417,
    "tp": 0.9417,
    "sl": 0.9417,
    "leverage": "6x",
    "pop": 50,
    "signal": "Neutral",
    "ema_boost_applied": false,
    "estimated_profit": "0.00%",
    "analysis_log": {
      "buy_score": 15,
      "sell_score": 15,
      "profit_ceiling_ok": true,
      "min_profit_ok": false,
      "downgrade_reason": "N/A"
    },
    "indicators": {
      "rsi5m": 50.73155471409589,
      "macd5m": {
        "macd": -0.0024157838844171,
        "signal": -0.004318110727837766,
        "histogram": 0.001902326843420666
      },
      "boll5m": {
        "upper": 0.9447209140315791,
        "middle": 0.935665,
        "lower": 0.9266090859684208
      },
      "cci5m": 119.69662836975195,
      "marketTrend": -5,
      "volProfile": {
        "bullish_score": 3,
        "bearish_score": 0
      },
      "ema50_5m": 0.9453600877029605
    }
  },
  {
    "coin": "AVAXUSDT",
    "price": 23.723,
    "tp": 23.6029,
    "sl": 23.8431,
    "leverage": "6x",
    "pop": 60,
    "signal": "Sell",
    "ema_boost_applied": false,
    "estimated_profit": "2.53%",
    "analysis_log": {
      "buy_score": -10,
      "sell_score": 15,
      "initial_signal": "Sell",
      "base_score_ok": false,
      "confluence_ok": false,
      "vol_profile_ok": true,
      "market_trend_ok": true,
      "macd_conflict_ok": false,
      "profit_ceiling_ok": true,
      "min_profit_ok": true,
      "downgrade_reason": "N/A"
    },
    "indicators": {
      "rsi5m": 47.92747772580266,
      "macd5m": {
        "macd": -0.032084725911513345,
        "signal": -0.05396770390758149,
        "histogram": 0.021882977996068143
      },
      "boll5m": {
        "upper": 23.79342167396863,
        "middle": 23.671799999999998,
        "lower": 23.550178326031364
      },
      "cci5m": 82.85822881033423,
      "marketTrend": -5,
      "volProfile": {
        "bullish_score": 0,
        "bearish_score": 3
      },
      "ema50_5m": 23.785627996411687
    }
  },
  {
    "coin": "TRUMPUSDT",
    "price": 9.103,
    "tp": 9.0612,
    "sl": 9.1448,
    "leverage": "6x",
    "pop": 60,
    "signal": "Sell",
    "ema_boost_applied": false,
    "estimated_profit": "2.30%",
    "analysis_log": {
      "buy_score": -10,
      "sell_score": 15,
      "initial_signal": "Sell",
      "base_score_ok": false,
      "confluence_ok": false,
      "vol_profile_ok": true,
      "market_trend_ok": true,
      "macd_conflict_ok": false,
      "profit_ceiling_ok": true,
      "min_profit_ok": true,
      "downgrade_reason": "N/A"
    },
    "indicators": {
      "rsi5m": 42.6691118201543,
      "macd5m": {
        "macd": -0.013708547391786396,
        "signal": -0.01490885277696283,
        "histogram": 0.0012003053851764329
      },
      "boll5m": {
        "upper": 9.153830979421212,
        "middle": 9.1113,
        "lower": 9.068769020578788
      },
      "cci5m": -28.898956617244377,
      "marketTrend": -5,
      "volProfile": {
        "bullish_score": 0,
        "bearish_score": 3
      },
      "ema50_5m": 9.133606102855516
    }
  },
  {
    "coin": "HYPEUSDT",
    "price": 46.766,
    "tp": 46.5019,
    "sl": 47.0301,
    "leverage": "6x",
    "pop": 60,
    "signal": "Sell",
    "ema_boost_applied": false,
    "estimated_profit": "2.82%",
    "analysis_log": {
      "buy_score": -10,
      "sell_score": 15,
      "initial_signal": "Sell",
      "base_score_ok": false,
      "confluence_ok": false,
      "vol_profile_ok": true,
      "market_trend_ok": true,
      "macd_conflict_ok": false,
      "profit_ceiling_ok": true,
      "min_profit_ok": true,
      "downgrade_reason": "N/A"
    },
    "indicators": {
      "rsi5m": 45.209986390373444,
      "macd5m": {
        "macd": -0.07097094254717717,
        "signal": -0.11122459570983888,
        "histogram": 0.040253653162661704
      },
      "boll5m": {
        "upper": 46.94792542959431,
        "middle": 46.7171,
        "lower": 46.4862745704057
      },
      "cci5m": 47.70086458505478,
      "marketTrend": -5,
      "volProfile": {
        "bullish_score": 0,
        "bearish_score": 3
      },
      "ema50_5m": 46.99655454987283
    }
  },
  {
    "coin": "SKLUSDT",
    "price": 0.0366,
    "tp": 0.0358,
    "sl": 0.0373,
    "leverage": "7x",
    "pop": 67,
    "signal": "Sell",
    "ema_boost_applied": false,
    "estimated_profit": "10.48%",
    "analysis_log": {
      "buy_score": 15,
      "sell_score": 30,
      "initial_signal": "Sell",
      "base_score_ok": true,
      "confluence_ok": false,
      "vol_profile_ok": false,
      "market_trend_ok": true,
      "macd_conflict_ok": false,
      "profit_ceiling_ok": false,
      "min_profit_ok": true,
      "downgrade_reason": "N/A"
    },
    "indicators": {
      "rsi5m": 68.10458348532566,
      "macd5m": {
        "macd": 0.00027315294214466657,
        "signal": 5.269369865231366e-05,
        "histogram": 0.0002204592434923529
      },
      "boll5m": {
        "upper": 0.036605096038670064,
        "middle": 0.035238,
        "lower": 0.03387090396132993
      },
      "cci5m": 211.7452440033099,
      "marketTrend": -5,
      "volProfile": {
        "bullish_score": 3,
        "bearish_score": 0
      },
      "ema50_5m": 0.035446778643419656
    }
  },
  {
    "coin": "ARBUSDT",
    "price": 0.4788,
    "tp": 0.4788,
    "sl": 0.4788,
    "leverage": "6x",
    "pop": 50,
    "signal": "Neutral",
    "ema_boost_applied": false,
    "estimated_profit": "0.00%",
    "analysis_log": {
      "buy_score": 15,
      "sell_score": 15,
      "profit_ceiling_ok": true,
      "min_profit_ok": false,
      "downgrade_reason": "N/A"
    },
    "indicators": {
      "rsi5m": 47.68877079394472,
      "macd5m": {
        "macd": -0.0007505336046750855,
        "signal": -0.0012518304729010154,
        "histogram": 0.00050129686822593
      },
      "boll5m": {
        "upper": 0.48059544834202295,
        "middle": 0.47772499999999996,
        "lower": 0.47485455165797696
      },
      "cci5m": 101.24028247582065,
      "marketTrend": -5,
      "volProfile": {
        "bullish_score": 0,
        "bearish_score": 3
      },
      "ema50_5m": 0.4805291498245032
    }
  },
  {
    "coin": "LTCUSDT",
    "price": 118.03,
    "tp": 117.5583,
    "sl": 118.5017,
    "leverage": "6x",
    "pop": 60,
    "signal": "Sell",
    "ema_boost_applied": false,
    "estimated_profit": "2.00%",
    "analysis_log": {
      "buy_score": -10,
      "sell_score": 15,
      "initial_signal": "Sell",
      "base_score_ok": false,
      "confluence_ok": false,
      "vol_profile_ok": true,
      "market_trend_ok": true,
      "macd_conflict_ok": false,
      "profit_ceiling_ok": true,
      "min_profit_ok": false,
      "downgrade_reason": "N/A"
    },
    "indicators": {
      "rsi5m": 40.76735769306443,
      "macd5m": {
        "macd": -0.0839542010124461,
        "signal": -0.089292134202268,
        "histogram": 0.005337933189821897
      },
      "boll5m": {
        "upper": 118.77527347386024,
        "middle": 118.322,
        "lower": 117.86872652613977
      },
      "cci5m": -80.58071796748446,
      "marketTrend": -5,
      "volProfile": {
        "bullish_score": 0,
        "bearish_score": 3
      },
      "ema50_5m": 118.51572544743689
    }
  },
  {
    "coin": "WIFUSDT",
    "price": 0.8802,
    "tp": 0.8802,
    "sl": 0.8802,
    "leverage": "6x",
    "pop": 50,
    "signal": "Neutral",
    "ema_boost_applied": false,
    "estimated_profit": "0.00%",
    "analysis_log": {
      "buy_score": 15,
      "sell_score": 15,
      "profit_ceiling_ok": true,
      "min_profit_ok": false,
      "downgrade_reason": "N/A"
    },
    "indicators": {
      "rsi5m": 54.33645304627265,
      "macd5m": {
        "macd": 0.00020317927804403002,
        "signal": -0.00055400489262482,
        "histogram": 0.00075718417066885
      },
      "boll5m": {
        "upper": 0.8825429616683309,
        "middle": 0.8768750000000001,
        "lower": 0.8712070383316692
      },
      "cci5m": 112.80772826425638,
      "marketTrend": -5,
      "volProfile": {
        "bullish_score": 3,
        "bearish_score": 0
      },
      "ema50_5m": 0.8787968519183197
    }
  },
  {
    "coin": "PENGUUSDT",
    "price": 0.0326,
    "tp": 0.0326,
    "sl": 0.0326,
    "leverage": "6x",
    "pop": 50,
    "signal": "Neutral",
    "ema_boost_applied": false,
    "estimated_profit": "0.00%",
    "analysis_log": {
      "buy_score": 15,
      "sell_score": 15,
      "profit_ceiling_ok": true,
      "min_profit_ok": false,
      "downgrade_reason": "N/A"
    },
    "indicators": {
      "rsi5m": 56.59242321108181,
      "macd5m": {
        "macd": 1.9102092462738862e-05,
        "signal": -1.8847709743838825e-05,
        "histogram": 3.794980220657769e-05
      },
      "boll5m": {
        "upper": 0.032695235543494856,
        "middle": 0.0324256,
        "lower": 0.03215596445650514
      },
      "cci5m": 123.47476887094444,
      "marketTrend": -5,
      "volProfile": {
        "bullish_score": 0,
        "bearish_score": 3
      },
      "ema50_5m": 0.03249646128917943
    }
  },
  {
    "coin": "UNIUSDT",
    "price": 11.011,
    "tp": 11.011,
    "sl": 11.011,
    "leverage": "6x",
    "pop": 50,
    "signal": "Neutral",
    "ema_boost_applied": false,
    "estimated_profit": "0.00%",
    "analysis_log": {
      "buy_score": 15,
      "sell_score": 15,
      "profit_ceiling_ok": true,
      "min_profit_ok": false,
      "downgrade_reason": "N/A"
    },
    "indicators": {
      "rsi5m": 59.61945319081627,
      "macd5m": {
        "macd": 0.018853406548508644,
        "signal": -0.006883435890707125,
        "histogram": 0.02573684243921577
      },
      "boll5m": {
        "upper": 11.064555101829429,
        "middle": 10.90135,
        "lower": 10.738144898170573
      },
      "cci5m": 147.3358475969438,
      "marketTrend": -5,
      "volProfile": {
        "bullish_score": 0,
        "bearish_score": 3
      },
      "ema50_5m": 10.938555600516379
    }
  },
  {
    "coin": "PUMPUSDT",
    "price": 0.0034,
    "tp": 0.0034,
    "sl": 0.0034,
    "leverage": "6x",
    "pop": 60,
    "signal": "Sell",
    "ema_boost_applied": false,
    "estimated_profit": "4.28%",
    "analysis_log": {
      "buy_score": -10,
      "sell_score": 15,
      "initial_signal": "Sell",
      "base_score_ok": false,
      "confluence_ok": false,
      "vol_profile_ok": true,
      "market_trend_ok": true,
      "macd_conflict_ok": false,
      "profit_ceiling_ok": true,
      "min_profit_ok": true,
      "downgrade_reason": "N/A"
    },
    "indicators": {
      "rsi5m": 43.62347581203914,
      "macd5m": {
        "macd": -1.049732413679243e-05,
        "signal": -1.3724101120920425e-05,
        "histogram": 3.226776984127995e-06
      },
      "boll5m": {
        "upper": 0.003439659020618974,
        "middle": 0.00341865,
        "lower": 0.0033976409793810263
      },
      "cci5m": 17.608897126969136,
      "marketTrend": -5,
      "volProfile": {
        "bullish_score": 5,
        "bearish_score": 5
      },
      "ema50_5m": 0.003445775148082918
    }
  },
  {
    "coin": "MAGICUSDT",
    "price": 0.2466,
    "tp": 0.2448,
    "sl": 0.2484,
    "leverage": "6x",
    "pop": 60,
    "signal": "Sell",
    "ema_boost_applied": false,
    "estimated_profit": "3.74%",
    "analysis_log": {
      "buy_score": -10,
      "sell_score": 15,
      "initial_signal": "Sell",
      "base_score_ok": false,
      "confluence_ok": false,
      "vol_profile_ok": true,
      "market_trend_ok": true,
      "macd_conflict_ok": false,
      "profit_ceiling_ok": true,
      "min_profit_ok": true,
      "downgrade_reason": "N/A"
    },
    "indicators": {
      "rsi5m": 47.473020553811445,
      "macd5m": {
        "macd": -0.00039668340076459696,
        "signal": -0.0005471815071065101,
        "histogram": 0.00015049810634191313
      },
      "boll5m": {
        "upper": 0.24792165011293113,
        "middle": 0.24646000000000004,
        "lower": 0.24499834988706895
      },
      "cci5m": 45.18743667680077,
      "marketTrend": -5,
      "volProfile": {
        "bullish_score": 0,
        "bearish_score": 3
      },
      "ema50_5m": 0.24751223454293486
    }
  },
  {
    "coin": "1000BONKUSDT",
    "price": 0.0239,
    "tp": 0.0238,
    "sl": 0.024,
    "leverage": "6x",
    "pop": 60,
    "signal": "Sell",
    "ema_boost_applied": false,
    "estimated_profit": "2.99%",
    "analysis_log": {
      "buy_score": -10,
      "sell_score": 15,
      "initial_signal": "Sell",
      "base_score_ok": false,
      "confluence_ok": false,
      "vol_profile_ok": true,
      "market_trend_ok": true,
      "macd_conflict_ok": false,
      "profit_ceiling_ok": true,
      "min_profit_ok": true,
      "downgrade_reason": "N/A"
    },
    "indicators": {
      "rsi5m": 50.68513780423604,
      "macd5m": {
        "macd": -1.4542120401195291e-05,
        "signal": -2.6996003833666278e-05,
        "histogram": 1.2453883432470987e-05
      },
      "boll5m": {
        "upper": 0.023985306117414756,
        "middle": 0.0238621,
        "lower": 0.023738893882585245
      },
      "cci5m": 66.29200327830297,
      "marketTrend": -5,
      "volProfile": {
        "bullish_score": 0,
        "bearish_score": 3
      },
      "ema50_5m": 0.023911976634565714
    }
  },
  {
    "coin": "AAVEUSDT",
    "price": 291.58,
    "tp": 290.205,
    "sl": 292.955,
    "leverage": "9x",
    "pop": 89,
    "signal": "Sell",
    "ema_boost_applied": false,
    "estimated_profit": "2.36%",
    "analysis_log": {
      "buy_score": 5,
      "sell_score": 40,
      "initial_signal": "Sell",
      "base_score_ok": true,
      "confluence_ok": false,
      "vol_profile_ok": true,
      "market_trend_ok": true,
      "macd_conflict_ok": false,
      "profit_ceiling_ok": true,
      "min_profit_ok": true,
      "downgrade_reason": "N/A"
    },
    "indicators": {
      "rsi5m": 33.83077849731745,
      "macd5m": {
        "macd": -0.9012801753175381,
        "signal": -1.052993952164034,
        "histogram": 0.15171377684649578
      },
      "boll5m": {
        "upper": 293.13831409130967,
        "middle": 292.3225,
        "lower": 291.5066859086903
      },
      "cci5m": -174.9239196591765,
      "marketTrend": -5,
      "volProfile": {
        "bullish_score": 0,
        "bearish_score": 3
      },
      "ema50_5m": 294.7088129708557
    }
  },
  {
    "coin": "PROVEUSDT",
    "price": 1.3113,
    "tp": 1.3113,
    "sl": 1.3113,
    "leverage": "6x",
    "pop": 50,
    "signal": "Neutral",
    "ema_boost_applied": false,
    "estimated_profit": "0.00%",
    "analysis_log": {
      "buy_score": 15,
      "sell_score": 15,
      "profit_ceiling_ok": true,
      "min_profit_ok": false,
      "downgrade_reason": "N/A"
    },
    "indicators": {
      "rsi5m": 54.27265789233717,
      "macd5m": {
        "macd": 0.0002759782455121762,
        "signal": -0.002754889945025928,
        "histogram": 0.0030308681905381043
      },
      "boll5m": {
        "upper": 1.3172253053811367,
        "middle": 1.299775,
        "lower": 1.2823246946188631
      },
      "cci5m": 122.59191509698124,
      "marketTrend": -5,
      "volProfile": {
        "bullish_score": 3,
        "bearish_score": 0
      },
      "ema50_5m": 1.3079508414999894
    }
  },
  {
    "coin": "LAUSDT",
    "price": 0.3718,
    "tp": 0.3632,
    "sl": 0.3804,
    "leverage": "7x",
    "pop": 75,
    "signal": "Sell",
    "ema_boost_applied": false,
    "estimated_profit": "11.58%",
    "analysis_log": {
      "buy_score": 5,
      "sell_score": 15,
      "initial_signal": "Sell",
      "base_score_ok": false,
      "confluence_ok": false,
      "vol_profile_ok": true,
      "market_trend_ok": true,
      "macd_conflict_ok": false,
      "profit_ceiling_ok": false,
      "min_profit_ok": true,
      "downgrade_reason": "N/A"
    },
    "indicators": {
      "rsi5m": 32.12351094035853,
      "macd5m": {
        "macd": -0.0064420227483610315,
        "signal": -0.0073113140875957685,
        "histogram": 0.000869291339234737
      },
      "boll5m": {
        "upper": 0.3870042345186321,
        "middle": 0.377365,
        "lower": 0.3677257654813679
      },
      "cci5m": -86.82948855864201,
      "marketTrend": -5,
      "volProfile": {
        "bullish_score": 0,
        "bearish_score": 3
      },
      "ema50_5m": 0.39194054171164133
    }
  },
  {
    "coin": "DOTUSDT",
    "price": 3.924,
    "tp": 3.9044,
    "sl": 3.9436,
    "leverage": "6x",
    "pop": 60,
    "signal": "Sell",
    "ema_boost_applied": false,
    "estimated_profit": "2.50%",
    "analysis_log": {
      "buy_score": -10,
      "sell_score": 15,
      "initial_signal": "Sell",
      "base_score_ok": false,
      "confluence_ok": false,
      "vol_profile_ok": false,
      "market_trend_ok": true,
      "macd_conflict_ok": false,
      "profit_ceiling_ok": true,
      "min_profit_ok": true,
      "downgrade_reason": "N/A"
    },
    "indicators": {
      "rsi5m": 50.078360149576135,
      "macd5m": {
        "macd": -0.0017819139785038018,
        "signal": -0.0038293833223127455,
        "histogram": 0.0020474693438089437
      },
      "boll5m": {
        "upper": 3.9367952961640564,
        "middle": 3.918,
        "lower": 3.899204703835944
      },
      "cci5m": 77.97177708681784,
      "marketTrend": -5,
      "volProfile": {
        "bullish_score": 3,
        "bearish_score": 0
      },
      "ema50_5m": 3.9249225571268656
    }
  },
  {
    "coin": "TRXUSDT",
    "price": 0.3512,
    "tp": 0.3506,
    "sl": 0.3518,
    "leverage": "7x",
    "pop": 75,
    "signal": "Sell",
    "ema_boost_applied": false,
    "estimated_profit": "0.91%",
    "analysis_log": {
      "buy_score": 5,
      "sell_score": 15,
      "initial_signal": "Sell",
      "base_score_ok": false,
      "confluence_ok": false,
      "vol_profile_ok": true,
      "market_trend_ok": true,
      "macd_conflict_ok": true,
      "profit_ceiling_ok": true,
      "min_profit_ok": false,
      "downgrade_reason": "N/A"
    },
    "indicators": {
      "rsi5m": 31.12625704873612,
      "macd5m": {
        "macd": -0.0005436277660607614,
        "signal": -0.0004896348430294894,
        "histogram": -5.399292303127196e-05
      },
      "boll5m": {
        "upper": 0.35361504978579134,
        "middle": 0.352135,
        "lower": 0.3506549502142086
      },
      "cci5m": -94.26283313640444,
      "marketTrend": -5,
      "volProfile": {
        "bullish_score": 0,
        "bearish_score": 3
      },
      "ema50_5m": 0.3526981658933982
    }
  },
  {
    "coin": "LDOUSDT",
    "price": 1.3706,
    "tp": 1.3599,
    "sl": 1.3813,
    "leverage": "6x",
    "pop": 60,
    "signal": "Sell",
    "ema_boost_applied": false,
    "estimated_profit": "3.92%",
    "analysis_log": {
      "buy_score": -10,
      "sell_score": 15,
      "initial_signal": "Sell",
      "base_score_ok": false,
      "confluence_ok": false,
      "vol_profile_ok": true,
      "market_trend_ok": true,
      "macd_conflict_ok": false,
      "profit_ceiling_ok": true,
      "min_profit_ok": true,
      "downgrade_reason": "N/A"
    },
    "indicators": {
      "rsi5m": 40.41623057217158,
      "macd5m": {
        "macd": -0.0021066601838772847,
        "signal": -0.0027375170267840187,
        "histogram": 0.000630856842906734
      },
      "boll5m": {
        "upper": 1.3845867947336206,
        "middle": 1.37476,
        "lower": 1.3649332052663794
      },
      "cci5m": -51.37699606572567,
      "marketTrend": -5,
      "volProfile": {
        "bullish_score": 0,
        "bearish_score": 3
      },
      "ema50_5m": 1.383621346920877
    }
  },
  {
    "coin": "XLMUSDT",
    "price": 0.4254,
    "tp": 0.4234,
    "sl": 0.4274,
    "leverage": "7x",
    "pop": 75,
    "signal": "Sell",
    "ema_boost_applied": false,
    "estimated_profit": "2.34%",
    "analysis_log": {
      "buy_score": 5,
      "sell_score": 15,
      "initial_signal": "Sell",
      "base_score_ok": false,
      "confluence_ok": false,
      "vol_profile_ok": true,
      "market_trend_ok": true,
      "macd_conflict_ok": true,
      "profit_ceiling_ok": true,
      "min_profit_ok": true,
      "downgrade_reason": "N/A"
    },
    "indicators": {
      "rsi5m": 34.39934314181393,
      "macd5m": {
        "macd": -0.0009381221259828765,
        "signal": -0.000848391832034319,
        "histogram": -8.973029394855744e-05
      },
      "boll5m": {
        "upper": 0.42957462118199946,
        "middle": 0.4270275,
        "lower": 0.42448037881800055
      },
      "cci5m": -88.60122045144782,
      "marketTrend": -5,
      "volProfile": {
        "bullish_score": 0,
        "bearish_score": 3
      },
      "ema50_5m": 0.4279441488639304
    }
  },
  {
    "coin": "AIOUSDT",
    "price": 0.0822,
    "tp": 0.0801,
    "sl": 0.0843,
    "leverage": "9x",
    "pop": 89,
    "signal": "Sell",
    "ema_boost_applied": false,
    "estimated_profit": "12.79%",
    "analysis_log": {
      "buy_score": 5,
      "sell_score": 40,
      "initial_signal": "Sell",
      "base_score_ok": true,
      "confluence_ok": false,
      "vol_profile_ok": true,
      "market_trend_ok": true,
      "macd_conflict_ok": false,
      "profit_ceiling_ok": false,
      "min_profit_ok": true,
      "downgrade_reason": "N/A"
    },
    "indicators": {
      "rsi5m": 33.705417751661514,
      "macd5m": {
        "macd": -0.0010671081355190515,
        "signal": -0.0010823408204794155,
        "histogram": 1.5232684960364042e-05
      },
      "boll5m": {
        "upper": 0.08553767826187313,
        "middle": 0.0835795,
        "lower": 0.08162132173812688
      },
      "cci5m": -103.51771442955136,
      "marketTrend": -5,
      "volProfile": {
        "bullish_score": 0,
        "bearish_score": 3
      },
      "ema50_5m": 0.08602763412779764
    }
  },
  {
    "coin": "NEARUSDT",
    "price": 2.708,
    "tp": 2.6926,
    "sl": 2.7234,
    "leverage": "6x",
    "pop": 60,
    "signal": "Sell",
    "ema_boost_applied": false,
    "estimated_profit": "2.85%",
    "analysis_log": {
      "buy_score": -10,
      "sell_score": 15,
      "initial_signal": "Sell",
      "base_score_ok": false,
      "confluence_ok": false,
      "vol_profile_ok": true,
      "market_trend_ok": true,
      "macd_conflict_ok": false,
      "profit_ceiling_ok": true,
      "min_profit_ok": true,
      "downgrade_reason": "N/A"
    },
    "indicators": {
      "rsi5m": 48.55923146591196,
      "macd5m": {
        "macd": -0.0023352529970961378,
        "signal": -0.004368315711800583,
        "histogram": 0.0020330627147044453
      },
      "boll5m": {
        "upper": 2.717380773598258,
        "middle": 2.7041,
        "lower": 2.690819226401742
      },
      "cci5m": 75.57811618725303,
      "marketTrend": -5,
      "volProfile": {
        "bullish_score": 0,
        "bearish_score": 3
      },
      "ema50_5m": 2.713880900755965
    }
  },
  {
    "coin": "USELESSUSDT",
    "price": 0.3161,
    "tp": 0.308,
    "sl": 0.3242,
    "leverage": "6x",
    "pop": 60,
    "signal": "Sell",
    "ema_boost_applied": false,
    "estimated_profit": "12.75%",
    "analysis_log": {
      "buy_score": -10,
      "sell_score": 15,
      "initial_signal": "Sell",
      "base_score_ok": false,
      "confluence_ok": false,
      "vol_profile_ok": true,
      "market_trend_ok": true,
      "macd_conflict_ok": false,
      "profit_ceiling_ok": false,
      "min_profit_ok": true,
      "downgrade_reason": "N/A"
    },
    "indicators": {
      "rsi5m": 44.550747561244336,
      "macd5m": {
        "macd": -0.004185719368386076,
        "signal": -0.005319645603585812,
        "histogram": 0.001133926235199736
      },
      "boll5m": {
        "upper": 0.3209986601472085,
        "middle": 0.314155,
        "lower": 0.3073113398527915
      },
      "cci5m": 61.40063367202051,
      "marketTrend": -5,
      "volProfile": {
        "bullish_score": 0,
        "bearish_score": 3
      },
      "ema50_5m": 0.32314088380330314
    }
  },
  {
    "coin": "OPUSDT",
    "price": 0.7222,
    "tp": 0.7222,
    "sl": 0.7222,
    "leverage": "6x",
    "pop": 50,
    "signal": "Neutral",
    "ema_boost_applied": false,
    "estimated_profit": "0.00%",
    "analysis_log": {
      "buy_score": 15,
      "sell_score": 15,
      "profit_ceiling_ok": true,
      "min_profit_ok": false,
      "downgrade_reason": "N/A"
    },
    "indicators": {
      "rsi5m": 55.39576327522203,
      "macd5m": {
        "macd": 0.0002697077406614845,
        "signal": -0.0005096875405729753,
        "histogram": 0.0007793952812344598
      },
      "boll5m": {
        "upper": 0.7242546037134479,
        "middle": 0.71911,
        "lower": 0.7139653962865522
      },
      "cci5m": 116.23571370673916,
      "marketTrend": -5,
      "volProfile": {
        "bullish_score": 0,
        "bearish_score": 3
      },
      "ema50_5m": 0.7214856358186593
    }
  },
  {
    "coin": "TIAUSDT",
    "price": 1.7876,
    "tp": 1.7876,
    "sl": 1.7876,
    "leverage": "6x",
    "pop": 50,
    "signal": "Neutral",
    "ema_boost_applied": false,
    "estimated_profit": "0.00%",
    "analysis_log": {
      "buy_score": 15,
      "sell_score": 15,
      "profit_ceiling_ok": true,
      "min_profit_ok": false,
      "downgrade_reason": "N/A"
    },
    "indicators": {
      "rsi5m": 59.429088220258315,
      "macd5m": {
        "macd": 0.0006693594751030485,
        "signal": -0.0019747619973637135,
        "histogram": 0.002644121472466762
      },
      "boll5m": {
        "upper": 1.7907006191524133,
        "middle": 1.77531,
        "lower": 1.7599193808475866
      },
      "cci5m": 142.31043653110603,
      "marketTrend": -5,
      "volProfile": {
        "bullish_score": 0,
        "bearish_score": 3
      },
      "ema50_5m": 1.7819790651522358
    }
  },
  {
    "coin": "1000SHIBUSDT",
    "price": 0.0129,
    "tp": 0.0128,
    "sl": 0.0129,
    "leverage": "6x",
    "pop": 60,
    "signal": "Sell",
    "ema_boost_applied": false,
    "estimated_profit": "2.34%",
    "analysis_log": {
      "buy_score": -10,
      "sell_score": 15,
      "initial_signal": "Sell",
      "base_score_ok": false,
      "confluence_ok": false,
      "vol_profile_ok": true,
      "market_trend_ok": true,
      "macd_conflict_ok": false,
      "profit_ceiling_ok": true,
      "min_profit_ok": true,
      "downgrade_reason": "N/A"
    },
    "indicators": {
      "rsi5m": 43.68583451835311,
      "macd5m": {
        "macd": -1.6123062338967153e-05,
        "signal": -2.248011384155882e-05,
        "histogram": 6.357051502591668e-06
      },
      "boll5m": {
        "upper": 0.012944330240324264,
        "middle": 0.0128897,
        "lower": 0.012835069759675737
      },
      "cci5m": 24.242424242412458,
      "marketTrend": -5,
      "volProfile": {
        "bullish_score": 0,
        "bearish_score": 3
      },
      "ema50_5m": 0.012932395495124921
    }
  },
  {
    "coin": "HBARUSDT",
    "price": 0.2495,
    "tp": 0.2482,
    "sl": 0.2508,
    "leverage": "6x",
    "pop": 60,
    "signal": "Sell",
    "ema_boost_applied": false,
    "estimated_profit": "2.70%",
    "analysis_log": {
      "buy_score": -10,
      "sell_score": 15,
      "initial_signal": "Sell",
      "base_score_ok": false,
      "confluence_ok": false,
      "vol_profile_ok": true,
      "market_trend_ok": true,
      "macd_conflict_ok": false,
      "profit_ceiling_ok": true,
      "min_profit_ok": true,
      "downgrade_reason": "N/A"
    },
    "indicators": {
      "rsi5m": 49.10405284570238,
      "macd5m": {
        "macd": -7.38022635389246e-05,
        "signal": -0.00018480447009841362,
        "histogram": 0.00011100220655948901
      },
      "boll5m": {
        "upper": 0.2506663064852281,
        "middle": 0.24932950000000004,
        "lower": 0.24799269351477196
      },
      "cci5m": 45.06895026735396,
      "marketTrend": -5,
      "volProfile": {
        "bullish_score": 0,
        "bearish_score": 3
      },
      "ema50_5m": 0.2496740440269819
    }
  },
  {
    "coin": "CRVUSDT",
    "price": 0.863,
    "tp": 0.8566,
    "sl": 0.8694,
    "leverage": "7x",
    "pop": 67,
    "signal": "Sell",
    "ema_boost_applied": false,
    "estimated_profit": "3.72%",
    "analysis_log": {
      "buy_score": 15,
      "sell_score": 30,
      "initial_signal": "Sell",
      "base_score_ok": true,
      "confluence_ok": false,
      "vol_profile_ok": true,
      "market_trend_ok": true,
      "macd_conflict_ok": false,
      "profit_ceiling_ok": true,
      "min_profit_ok": true,
      "downgrade_reason": "N/A"
    },
    "indicators": {
      "rsi5m": 60.58614752537493,
      "macd5m": {
        "macd": 0.001116966105917605,
        "signal": -1.2465845648029165e-05,
        "histogram": 0.0011294319515656342
      },
      "boll5m": {
        "upper": 0.8647839164996524,
        "middle": 0.8572000000000001,
        "lower": 0.8496160835003478
      },
      "cci5m": 159.48365604830252,
      "marketTrend": -5,
      "volProfile": {
        "bullish_score": 0,
        "bearish_score": 3
      },
      "ema50_5m": 0.8599518170517954
    }
  },
  {
    "coin": "WLDUSDT",
    "price": 0.9822,
    "tp": 0.9765,
    "sl": 0.9879,
    "leverage": "6x",
    "pop": 60,
    "signal": "Sell",
    "ema_boost_applied": false,
    "estimated_profit": "2.92%",
    "analysis_log": {
      "buy_score": -10,
      "sell_score": 15,
      "initial_signal": "Sell",
      "base_score_ok": false,
      "confluence_ok": false,
      "vol_profile_ok": true,
      "market_trend_ok": true,
      "macd_conflict_ok": false,
      "profit_ceiling_ok": true,
      "min_profit_ok": true,
      "downgrade_reason": "N/A"
    },
    "indicators": {
      "rsi5m": 49.197403457221114,
      "macd5m": {
        "macd": -0.0005378839897797194,
        "signal": -0.0011435712251214758,
        "histogram": 0.0006056872353417564
      },
      "boll5m": {
        "upper": 0.9856719656730455,
        "middle": 0.9808299999999999,
        "lower": 0.9759880343269542
      },
      "cci5m": 69.44444444445023,
      "marketTrend": -5,
      "volProfile": {
        "bullish_score": 0,
        "bearish_score": 3
      },
      "ema50_5m": 0.9836297496381008
    }
  },
  {
    "coin": "ONDOUSDT",
    "price": 0.9854,
    "tp": 0.9807,
    "sl": 0.9901,
    "leverage": "6x",
    "pop": 60,
    "signal": "Sell",
    "ema_boost_applied": false,
    "estimated_profit": "2.41%",
    "analysis_log": {
      "buy_score": -10,
      "sell_score": 15,
      "initial_signal": "Sell",
      "base_score_ok": false,
      "confluence_ok": false,
      "vol_profile_ok": true,
      "market_trend_ok": true,
      "macd_conflict_ok": false,
      "profit_ceiling_ok": true,
      "min_profit_ok": true,
      "downgrade_reason": "N/A"
    },
    "indicators": {
      "rsi5m": 49.60909472215117,
      "macd5m": {
        "macd": -0.00044927536194860895,
        "signal": -0.0009708195311087866,
        "histogram": 0.0005215441691601776
      },
      "boll5m": {
        "upper": 0.9879122824144576,
        "middle": 0.9839249999999999,
        "lower": 0.9799377175855423
      },
      "cci5m": 84.32883033753025,
      "marketTrend": -5,
      "volProfile": {
        "bullish_score": 0,
        "bearish_score": 3
      },
      "ema50_5m": 0.9863162768552416
    }
  },
  {
    "coin": "BCHUSDT",
    "price": 590.79,
    "tp": 589.2925,
    "sl": 592.2875,
    "leverage": "6x",
    "pop": 60,
    "signal": "Sell",
    "ema_boost_applied": false,
    "estimated_profit": "1.27%",
    "analysis_log": {
      "buy_score": -10,
      "sell_score": 15,
      "initial_signal": "Sell",
      "base_score_ok": false,
      "confluence_ok": false,
      "vol_profile_ok": true,
      "market_trend_ok": true,
      "macd_conflict_ok": false,
      "profit_ceiling_ok": true,
      "min_profit_ok": false,
      "downgrade_reason": "N/A"
    },
    "indicators": {
      "rsi5m": 48.87414856773208,
      "macd5m": {
        "macd": -0.1624112152271664,
        "signal": -0.45249512021972316,
        "histogram": 0.29008390499255676
      },
      "boll5m": {
        "upper": 591.8127416979555,
        "middle": 590.1385,
        "lower": 588.4642583020445
      },
      "cci5m": 86.89049552671703,
      "marketTrend": -5,
      "volProfile": {
        "bullish_score": 0,
        "bearish_score": 3
      },
      "ema50_5m": 591.6108586949439
    }
  },
  {
    "coin": "ALLUSDT",
    "price": 1.1033,
    "tp": 1.1033,
    "sl": 1.1033,
    "leverage": "6x",
    "pop": 50,
    "signal": "Neutral",
    "ema_boost_applied": false,
    "estimated_profit": "0.00%",
    "analysis_log": {
      "buy_score": 15,
      "sell_score": 15,
      "profit_ceiling_ok": true,
      "min_profit_ok": false,
      "downgrade_reason": "N/A"
    },
    "indicators": {
      "rsi5m": 55.67349301484661,
      "macd5m": {
        "macd": 5.5841586622307204e-05,
        "signal": -0.0009075097945501407,
        "histogram": 0.0009633513811724479
      },
      "boll5m": {
        "upper": 1.105353824563205,
        "middle": 1.0992849999999998,
        "lower": 1.0932161754367946
      },
      "cci5m": 121.26387702818086,
      "marketTrend": -5,
      "volProfile": {
        "bullish_score": 0,
        "bearish_score": 3
      },
      "ema50_5m": 1.102357944264598
    }
  },
  {
    "coin": "TAOUSDT",
    "price": 367.36,
    "tp": 365.6638,
    "sl": 369.0562,
    "leverage": "6x",
    "pop": 60,
    "signal": "Sell",
    "ema_boost_applied": false,
    "estimated_profit": "2.31%",
    "analysis_log": {
      "buy_score": -10,
      "sell_score": 15,
      "initial_signal": "Sell",
      "base_score_ok": false,
      "confluence_ok": false,
      "vol_profile_ok": true,
      "market_trend_ok": true,
      "macd_conflict_ok": false,
      "profit_ceiling_ok": true,
      "min_profit_ok": true,
      "downgrade_reason": "N/A"
    },
    "indicators": {
      "rsi5m": 44.81194728621047,
      "macd5m": {
        "macd": -0.42737706965277766,
        "signal": -0.6004712605371721,
        "histogram": 0.17309419088439448
      },
      "boll5m": {
        "upper": 368.95625177659554,
        "middle": 367.3815,
        "lower": 365.8067482234045
      },
      "cci5m": 17.249143416539262,
      "marketTrend": -5,
      "volProfile": {
        "bullish_score": 0,
        "bearish_score": 3
      },
      "ema50_5m": 368.6285269566955
    }
  },
  {
    "coin": "SEIUSDT",
    "price": 0.3196,
    "tp": 0.3177,
    "sl": 0.3215,
    "leverage": "6x",
    "pop": 60,
    "signal": "Sell",
    "ema_boost_applied": false,
    "estimated_profit": "2.97%",
    "analysis_log": {
      "buy_score": -10,
      "sell_score": 15,
      "initial_signal": "Sell",
      "base_score_ok": false,
      "confluence_ok": false,
      "vol_profile_ok": true,
      "market_trend_ok": true,
      "macd_conflict_ok": false,
      "profit_ceiling_ok": true,
      "min_profit_ok": true,
      "downgrade_reason": "N/A"
    },
    "indicators": {
      "rsi5m": 46.68917320336703,
      "macd5m": {
        "macd": -0.0002932090364421436,
        "signal": -0.0005508518090379599,
        "histogram": 0.0002576427725958163
      },
      "boll5m": {
        "upper": 0.32110084679861745,
        "middle": 0.31927000000000005,
        "lower": 0.31743915320138266
      },
      "cci5m": 47.677162151165966,
      "marketTrend": -5,
      "volProfile": {
        "bullish_score": 0,
        "bearish_score": 3
      },
      "ema50_5m": 0.3206849022021573
    }
  },
  {
    "coin": "APTUSDT",
    "price": 4.6528,
    "tp": 4.6288,
    "sl": 4.6768,
    "leverage": "6x",
    "pop": 60,
    "signal": "Sell",
    "ema_boost_applied": false,
    "estimated_profit": "2.58%",
    "analysis_log": {
      "buy_score": -10,
      "sell_score": 15,
      "initial_signal": "Sell",
      "base_score_ok": false,
      "confluence_ok": false,
      "vol_profile_ok": true,
      "market_trend_ok": true,
      "macd_conflict_ok": false,
      "profit_ceiling_ok": true,
      "min_profit_ok": true,
      "downgrade_reason": "N/A"
    },
    "indicators": {
      "rsi5m": 48.184091257562365,
      "macd5m": {
        "macd": -0.0033882276425361013,
        "signal": -0.00631398913928905,
        "histogram": 0.0029257614967529485
      },
      "boll5m": {
        "upper": 4.673150595433217,
        "middle": 4.647405,
        "lower": 4.621659404566783
      },
      "cci5m": 49.248068326699155,
      "marketTrend": -5,
      "volProfile": {
        "bullish_score": 0,
        "bearish_score": 3
      },
      "ema50_5m": 4.660467708585918
    }
  },
  {
    "coin": "SOONUSDT",
    "price": 0.3017,
    "tp": 0.2961,
    "sl": 0.3072,
    "leverage": "6x",
    "pop": 60,
    "signal": "Sell",
    "ema_boost_applied": false,
    "estimated_profit": "9.19%",
    "analysis_log": {
      "buy_score": -10,
      "sell_score": 15,
      "initial_signal": "Sell",
      "base_score_ok": false,
      "confluence_ok": false,
      "vol_profile_ok": true,
      "market_trend_ok": true,
      "macd_conflict_ok": false,
      "profit_ceiling_ok": false,
      "min_profit_ok": true,
      "downgrade_reason": "N/A"
    },
    "indicators": {
      "rsi5m": 47.35127344740993,
      "macd5m": {
        "macd": -0.0016897253433713622,
        "signal": -0.002215328355369687,
        "histogram": 0.000525603011998325
      },
      "boll5m": {
        "upper": 0.30501662943734054,
        "middle": 0.300463,
        "lower": 0.2959093705626594
      },
      "cci5m": 65.66750993613223,
      "marketTrend": -5,
      "volProfile": {
        "bullish_score": 0,
        "bearish_score": 3
      },
      "ema50_5m": 0.30542676408545405
    }
  },
  {
    "coin": "ETCUSDT",
    "price": 22.18,
    "tp": 22.0846,
    "sl": 22.2754,
    "leverage": "6x",
    "pop": 60,
    "signal": "Sell",
    "ema_boost_applied": false,
    "estimated_profit": "2.15%",
    "analysis_log": {
      "buy_score": -10,
      "sell_score": 15,
      "initial_signal": "Sell",
      "base_score_ok": false,
      "confluence_ok": false,
      "vol_profile_ok": true,
      "market_trend_ok": true,
      "macd_conflict_ok": false,
      "profit_ceiling_ok": true,
      "min_profit_ok": true,
      "downgrade_reason": "N/A"
    },
    "indicators": {
      "rsi5m": 44.953361546275055,
      "macd5m": {
        "macd": -0.012612465379511661,
        "signal": -0.01668370643166386,
        "histogram": 0.004071241052152199
      },
      "boll5m": {
        "upper": 22.27989898834049,
        "middle": 22.1977,
        "lower": 22.11550101165951
      },
      "cci5m": -16.879597367409517,
      "marketTrend": -5,
      "volProfile": {
        "bullish_score": 0,
        "bearish_score": 3
      },
      "ema50_5m": 22.227037988429167
    }
  },
  {
    "coin": "FILUSDT",
    "price": 2.484,
    "tp": 2.472,
    "sl": 2.496,
    "leverage": "6x",
    "pop": 60,
    "signal": "Sell",
    "ema_boost_applied": false,
    "estimated_profit": "2.41%",
    "analysis_log": {
      "buy_score": -10,
      "sell_score": 15,
      "initial_signal": "Sell",
      "base_score_ok": false,
      "confluence_ok": false,
      "vol_profile_ok": false,
      "market_trend_ok": true,
      "macd_conflict_ok": false,
      "profit_ceiling_ok": true,
      "min_profit_ok": true,
      "downgrade_reason": "N/A"
    },
    "indicators": {
      "rsi5m": 50.74521076829632,
      "macd5m": {
        "macd": -0.0008981506868126488,
        "signal": -0.0022975977202178478,
        "histogram": 0.001399447033405199
      },
      "boll5m": {
        "upper": 2.492324220995525,
        "middle": 2.4800999999999997,
        "lower": 2.4678757790044745
      },
      "cci5m": 85.12820512820497,
      "marketTrend": -5,
      "volProfile": {
        "bullish_score": 3,
        "bearish_score": 0
      },
      "ema50_5m": 2.484543387131813
    }
  },
  {
    "coin": "ETHFIUSDT",
    "price": 1.1351,
    "tp": 1.1271,
    "sl": 1.1431,
    "leverage": "6x",
    "pop": 60,
    "signal": "Sell",
    "ema_boost_applied": false,
    "estimated_profit": "3.53%",
    "analysis_log": {
      "buy_score": -10,
      "sell_score": 15,
      "initial_signal": "Sell",
      "base_score_ok": false,
      "confluence_ok": false,
      "vol_profile_ok": true,
      "market_trend_ok": true,
      "macd_conflict_ok": false,
      "profit_ceiling_ok": true,
      "min_profit_ok": true,
      "downgrade_reason": "N/A"
    },
    "indicators": {
      "rsi5m": 50.01756839980627,
      "macd5m": {
        "macd": -0.0005053122201865712,
        "signal": -0.0018230041055341283,
        "histogram": 0.0013176918853475572
      },
      "boll5m": {
        "upper": 1.1401308184420123,
        "middle": 1.131625,
        "lower": 1.123119181557988
      },
      "cci5m": 88.31558831558638,
      "marketTrend": -5,
      "volProfile": {
        "bullish_score": 0,
        "bearish_score": 3
      },
      "ema50_5m": 1.1376601326492553
    }
  },
  {
    "coin": "INJUSDT",
    "price": 14.312,
    "tp": 14.312,
    "sl": 14.312,
    "leverage": "6x",
    "pop": 50,
    "signal": "Neutral",
    "ema_boost_applied": false,
    "estimated_profit": "0.00%",
    "analysis_log": {
      "buy_score": 15,
      "sell_score": 15,
      "profit_ceiling_ok": true,
      "min_profit_ok": false,
      "downgrade_reason": "N/A"
    },
    "indicators": {
      "rsi5m": 54.14097149541276,
      "macd5m": {
        "macd": -0.0013102747016571215,
        "signal": -0.016602825087056725,
        "histogram": 0.015292550385399603
      },
      "boll5m": {
        "upper": 14.349098505340121,
        "middle": 14.2542,
        "lower": 14.15930149465988
      },
      "cci5m": 121.39955127038792,
      "marketTrend": -5,
      "volProfile": {
        "bullish_score": 0,
        "bearish_score": 3
      },
      "ema50_5m": 14.302463714721863
    }
  },
  {
    "coin": "TONUSDT",
    "price": 3.4976,
    "tp": 3.4817,
    "sl": 3.5135,
    "leverage": "6x",
    "pop": 60,
    "signal": "Sell",
    "ema_boost_applied": false,
    "estimated_profit": "2.28%",
    "analysis_log": {
      "buy_score": -10,
      "sell_score": 15,
      "initial_signal": "Sell",
      "base_score_ok": false,
      "confluence_ok": false,
      "vol_profile_ok": false,
      "market_trend_ok": true,
      "macd_conflict_ok": false,
      "profit_ceiling_ok": true,
      "min_profit_ok": true,
      "downgrade_reason": "N/A"
    },
    "indicators": {
      "rsi5m": 59.671032667748975,
      "macd5m": {
        "macd": 0.00742582758834498,
        "signal": 0.006216836083031812,
        "histogram": 0.0012089915053131676
      },
      "boll5m": {
        "upper": 3.5086757736423966,
        "middle": 3.48767,
        "lower": 3.4666642263576035
      },
      "cci5m": 99.02014723991041,
      "marketTrend": -5,
      "volProfile": {
        "bullish_score": 3,
        "bearish_score": 0
      },
      "ema50_5m": 3.4788713203152604
    }
  },
  {
    "coin": "CTSIUSDT",
    "price": 0.0867,
    "tp": 0.0816,
    "sl": 0.0918,
    "leverage": "6x",
    "pop": 60,
    "signal": "Sell",
    "ema_boost_applied": false,
    "estimated_profit": "29.54%",
    "analysis_log": {
      "buy_score": -10,
      "sell_score": 15,
      "initial_signal": "Sell",
      "base_score_ok": false,
      "confluence_ok": false,
      "vol_profile_ok": true,
      "market_trend_ok": true,
      "macd_conflict_ok": true,
      "profit_ceiling_ok": false,
      "min_profit_ok": true,
      "downgrade_reason": "N/A"
    },
    "indicators": {
      "rsi5m": 59.93368641237786,
      "macd5m": {
        "macd": 0.003991852693844153,
        "signal": 0.0040624747563861256,
        "histogram": -7.062206254197269e-05
      },
      "boll5m": {
        "upper": 0.09520627616112882,
        "middle": 0.08441,
        "lower": 0.07361372383887117
      },
      "cci5m": 43.597392553309106,
      "marketTrend": -5,
      "volProfile": {
        "bullish_score": 0,
        "bearish_score": 3
      },
      "ema50_5m": 0.07900105765487948
    }
  },
  {
    "coin": "ZORAUSDT",
    "price": 0.0962,
    "tp": 0.0953,
    "sl": 0.097,
    "leverage": "9x",
    "pop": 89,
    "signal": "Sell",
    "ema_boost_applied": false,
    "estimated_profit": "4.48%",
    "analysis_log": {
      "buy_score": 5,
      "sell_score": 40,
      "initial_signal": "Sell",
      "base_score_ok": true,
      "confluence_ok": false,
      "vol_profile_ok": true,
      "market_trend_ok": true,
      "macd_conflict_ok": false,
      "profit_ceiling_ok": true,
      "min_profit_ok": true,
      "downgrade_reason": "N/A"
    },
    "indicators": {
      "rsi5m": 34.69661909454511,
      "macd5m": {
        "macd": -0.00043143208140099254,
        "signal": -0.00044198131898521154,
        "histogram": 1.0549237584219005e-05
      },
      "boll5m": {
        "upper": 0.09748818074340514,
        "middle": 0.096785,
        "lower": 0.09608181925659486
      },
      "cci5m": -142.45880861850267,
      "marketTrend": -5,
      "volProfile": {
        "bullish_score": 0,
        "bearish_score": 3
      },
      "ema50_5m": 0.09769379850769142
    }
  },
  {
    "coin": "PENDLEUSDT",
    "price": 5.3264,
    "tp": 5.2849,
    "sl": 5.3679,
    "leverage": "6x",
    "pop": 60,
    "signal": "Sell",
    "ema_boost_applied": false,
    "estimated_profit": "3.90%",
    "analysis_log": {
      "buy_score": -10,
      "sell_score": 15,
      "initial_signal": "Sell",
      "base_score_ok": false,
      "confluence_ok": false,
      "vol_profile_ok": true,
      "market_trend_ok": true,
      "macd_conflict_ok": false,
      "profit_ceiling_ok": true,
      "min_profit_ok": true,
      "downgrade_reason": "N/A"
    },
    "indicators": {
      "rsi5m": 48.13159715801838,
      "macd5m": {
        "macd": 0.0006651105932098389,
        "signal": -0.0017222076401697023,
        "histogram": 0.002387318233379541
      },
      "boll5m": {
        "upper": 5.364595894168258,
        "middle": 5.3229299999999995,
        "lower": 5.281264105831741
      },
      "cci5m": 21.48604518062145,
      "marketTrend": -5,
      "volProfile": {
        "bullish_score": 0,
        "bearish_score": 3
      },
      "ema50_5m": 5.337227133888865
    }
  },
  {
    "coin": "INUSDT",
    "price": 0.0769,
    "tp": 0.0761,
    "sl": 0.0777,
    "leverage": "7x",
    "pop": 75,
    "signal": "Sell",
    "ema_boost_applied": false,
    "estimated_profit": "5.28%",
    "analysis_log": {
      "buy_score": 5,
      "sell_score": 15,
      "initial_signal": "Sell",
      "base_score_ok": false,
      "confluence_ok": false,
      "vol_profile_ok": true,
      "market_trend_ok": true,
      "macd_conflict_ok": false,
      "profit_ceiling_ok": true,
      "min_profit_ok": true,
      "downgrade_reason": "N/A"
    },
    "indicators": {
      "rsi5m": 39.96868729218291,
      "macd5m": {
        "macd": -0.00041891625408860267,
        "signal": -0.0005202246697978857,
        "histogram": 0.00010130841570928301
      },
      "boll5m": {
        "upper": 0.07792203841230684,
        "middle": 0.07711549999999999,
        "lower": 0.07630896158769314
      },
      "cci5m": -29.70462595582088,
      "marketTrend": -5,
      "volProfile": {
        "bullish_score": 0,
        "bearish_score": 3
      },
      "ema50_5m": 0.07826281832042202
    }
  },
  {
    "coin": "BERAUSDT",
    "price": 2.252,
    "tp": 2.2239,
    "sl": 2.2801,
    "leverage": "7x",
    "pop": 67,
    "signal": "Sell",
    "ema_boost_applied": false,
    "estimated_profit": "6.25%",
    "analysis_log": {
      "buy_score": 15,
      "sell_score": 30,
      "initial_signal": "Sell",
      "base_score_ok": true,
      "confluence_ok": false,
      "vol_profile_ok": false,
      "market_trend_ok": true,
      "macd_conflict_ok": false,
      "profit_ceiling_ok": true,
      "min_profit_ok": true,
      "downgrade_reason": "N/A"
    },
    "indicators": {
      "rsi5m": 65.12340690536388,
      "macd5m": {
        "macd": 0.013046860796542159,
        "signal": 0.007983894424292924,
        "histogram": 0.005062966372249235
      },
      "boll5m": {
        "upper": 2.2606511280119106,
        "middle": 2.2151000000000005,
        "lower": 2.1695488719880904
      },
      "cci5m": 140.29159627057146,
      "marketTrend": -5,
      "volProfile": {
        "bullish_score": 3,
        "bearish_score": 0
      },
      "ema50_5m": 2.209095601031094
    }
  },
  {
    "coin": "GALAUSDT",
    "price": 0.0169,
    "tp": 0.0169,
    "sl": 0.0169,
    "leverage": "6x",
    "pop": 50,
    "signal": "Neutral",
    "ema_boost_applied": false,
    "estimated_profit": "0.00%",
    "analysis_log": {
      "buy_score": 15,
      "sell_score": 15,
      "profit_ceiling_ok": true,
      "min_profit_ok": false,
      "downgrade_reason": "N/A"
    },
    "indicators": {
      "rsi5m": 54.88880961650956,
      "macd5m": {
        "macd": 1.6611286420348953e-05,
        "signal": 2.0102352088840704e-06,
        "histogram": 1.4601051211464883e-05
      },
      "boll5m": {
        "upper": 0.017017398853505842,
        "middle": 0.016884500000000004,
        "lower": 0.016751601146494165
      },
      "cci5m": 104.79797979798268,
      "marketTrend": -5,
      "volProfile": {
        "bullish_score": 3,
        "bearish_score": 0
      },
      "ema50_5m": 0.01688646245466924
    }
  },
  {
    "coin": "PNUTUSDT",
    "price": 0.2279,
    "tp": 0.2279,
    "sl": 0.2279,
    "leverage": "6x",
    "pop": 50,
    "signal": "Neutral",
    "ema_boost_applied": false,
    "estimated_profit": "0.00%",
    "analysis_log": {
      "buy_score": 15,
      "sell_score": 15,
      "profit_ceiling_ok": true,
      "min_profit_ok": false,
      "downgrade_reason": "N/A"
    },
    "indicators": {
      "rsi5m": 55.27750569754629,
      "macd5m": {
        "macd": 8.301792595039048e-05,
        "signal": -0.00010565598473557913,
        "histogram": 0.0001886739106859696
      },
      "boll5m": {
        "upper": 0.22845397088588001,
        "middle": 0.226968,
        "lower": 0.22548202911412
      },
      "cci5m": 109.14289958407512,
      "marketTrend": -5,
      "volProfile": {
        "bullish_score": 3,
        "bearish_score": 0
      },
      "ema50_5m": 0.22746634773732663
    }
  },
  {
    "coin": "VIRTUALUSDT",
    "price": 1.19,
    "tp": 1.183,
    "sl": 1.197,
    "leverage": "6x",
    "pop": 60,
    "signal": "Sell",
    "ema_boost_applied": false,
    "estimated_profit": "2.93%",
    "analysis_log": {
      "buy_score": -10,
      "sell_score": 15,
      "initial_signal": "Sell",
      "base_score_ok": false,
      "confluence_ok": false,
      "vol_profile_ok": true,
      "market_trend_ok": true,
      "macd_conflict_ok": false,
      "profit_ceiling_ok": true,
      "min_profit_ok": true,
      "downgrade_reason": "N/A"
    },
    "indicators": {
      "rsi5m": 48.84749170460159,
      "macd5m": {
        "macd": -0.000906782779816373,
        "signal": -0.0018928001214450598,
        "histogram": 0.0009860173416286868
      },
      "boll5m": {
        "upper": 1.1937128600375817,
        "middle": 1.18798,
        "lower": 1.1822471399624184
      },
      "cci5m": 80.8000212771676,
      "marketTrend": -5,
      "volProfile": {
        "bullish_score": 0,
        "bearish_score": 3
      },
      "ema50_5m": 1.192691793283937
    }
  }
]